say_no/__init__.py
say_no/say_no.py
say_no-4.2.0.dist-info/LICENSE
say_no-4.2.0.dist-info/METADATA
say_no-4.2.0.dist-info/WHEEL
say_no-4.2.0.dist-info/top_level.txt
say_no-4.2.0.dist-info/RECORD
