Metadata-Version: 2.1
Name: say-no
Version: 4.2.0
Summary: Tells someone/something "no" so that you dont have to!
Home-page: https://www.youtube.com/watch?v=PI5wz2pwXIg
Author: GDKID
Author-email: lazy@maildrop.cc
License: UNKNOWN
Project-URL: Bug Tracker, https://https://www.youtube.com/watch?v=PI5wz2pwXIg
Platform: UNKNOWN
Classifier: Programming Language :: Python :: 3
Classifier: License :: OSI Approved :: MIT License
Classifier: Operating System :: OS Independent
Requires-Python: >=3.6
License-File: LICENSE
